<?xml version="1.0" encoding="UTF-8"?>
<openerp>
    <data>
        
        <record id="view_clv_insured_card_tree_insured" model="ir.ui.view">
            <field name="name">clv_insured_card.tree</field>
            <field name="model">clv_insured_card</field>
            <field name="inherit_id" ref="view_clv_insured_card_tree"/>
            <field name="priority" eval="8" />
            <field name="arch" type="xml">
                <field name="code" position="after">
                    <field name="insured_id" />
                </field>
            </field>
        </record>

        <record id="view_clv_insured_card_form_insured" model="ir.ui.view">
            <field name="name">clv_insured_card.form</field>
            <field name="model">clv_insured_card</field>
            <field name="inherit_id" ref="view_clv_insured_card_form"/>
            <field name="priority" eval="8" />
            <field name="arch" type="xml">
                <div class="oe_title" position="inside">
                    <label for="insured_id"/>
                    <h3>
                        <field name="insured_id" placeholder="Insured..."/>
                    </h3>
                </div>
            </field>
        </record>

        <record id="view_clv_insured_card_search_insured" model="ir.ui.view">
            <field name="name">clv_insured_card.search</field>
            <field name="model">clv_insured_card</field>
            <field name="inherit_id" ref="view_clv_insured_card_search"/>
            <field name="priority" eval="8" />
            <field name="arch" type="xml">
                <field name="code" position="after">
                    <field name="insured_id" />
                </field>
                <group string="Group By..." position="inside">
                    <filter string="Insured" domain="[]" context="{'group_by': 'insured_id'}"/>
                </group>
            </field>
        </record>

        <record id="view_clv_insured_form_insured_card" model="ir.ui.view">
            <field name="name">clv_insured.form</field>
            <field name="model">clv_insured</field>
            <field name="inherit_id" ref="clv_insured.view_clv_insured_form"/>
            <field name="priority" eval="8" />
            <field name="arch" type="xml">
                <page string="Settings" position="before">
                    <page string="Insured Cards">
                        <group>
                            <field name="insured_card_ids" colspan="4" nolabel="1" />
                        </group>
                    </page>
                </page>
            </field>
        </record>

    </data>
</openerp>
